{"type": "FeatureCollection", "features": [{"type": "Feature", "geometry": {"type": "Point", "coordinates": [3.20878, 41.583099]}, "properties": {"var_data": [-0.063, 0.257, 0.007, 0.225, 1.157, -0.001, 0.0, 0.0, 1, 1, 1]}}, {"type": "Feature", "geometry": {"type": "Point", "coordinates": [3.24412, 41.583099]}, "properties": {"var_data": [-0.076, 0.259, 0.099, 0.23, 1.233, -0.005, 0.0, 0.0, 1, 4, 1]}}, {"type": "Feature", "geometry": {"type": "Point", "coordinates": [3.27946, 41.583099]}, "properties": {"var_data": [-0.043, 0.259, 0.031, 0.23, 1.423, -0.005, 0.0, 0.0, 1, 4, 1]}}, {"type": "Feature", "geometry": {"type": "Point", "coordinates": [3.3148, 41.583099]}, "properties": {"var_data": [-0.043, 0.259, 0.031, 0.23, 1.423, -0.005, 0.0, 0.0, 1, 4, 1]}}, {"type": "Feature", "geometry": {"type": "Point", "coordinates": [3.24412, 41.6101]}, "properties": {"var_data": [-0.065, 0.259, 0.031, 0.23, 1.162, -0.005, 0.0, 0.0, 1, 1, 1]}}, {"type": "Feature", "geometry": {"type": "Point", "coordinates": [3.27946, 41.6101]}, "properties": {"var_data": [-0.065, 0.259, 0.031, 0.23, 1.162, -0.005, 0.0, 0.0, 1, 1, 1]}}], "metadata": {"acknowledgment": "ICATMAR HF Radar Network has been established with the support of the European Maritime and Fisheries Fund, the European Maritime, Fisheries and Aquaculture Fund and the fund provided by the Government of Catalonia. The network has been designed, implemented and managed through the efforts of the Direcci\u00f3 General de Pol\u00edtica Mar\u00edtima i Pesca Sostenible (Government of Catalonia) and the Insitut de Ci\u00e8ncies del Mar (CSIC), Barcelona.", "area": "Mediterranean Sea", "citation": "These data were collected and made freely available by ICATMAR and the programs that contribute to it. Data was collected by the Government of Catalonia and processed by ICATMAR with the support of the European Maritime, Fisheries and Aquaculture Fund (EMFAF) and the Climatic Funds Program of the Government of Catalonia.", "Conventions": "CF-1.10", "date_created": "2024-03-20T17:52:18Z", "date_modified": "2024-03-20T17:52:18Z", "distribution_statement": "These data follow Copernicus standards; they are public and free of charge. User assumes all risk for use of data. User must display citation in any publication o product using data. User must contact ICATMAR prior to any commercial use of data.", "doi": "https://doi.org/10.20350/digitalCSIC/16139", "geospatial_lat_min": "39.5851", "geospatial_lat_max": "43.0681", "geospatial_lat_resolution": "0.027", "geospatial_lat_units": "degrees_north", "geospatial_lon_min": "0.06352", "geospatial_lon_max": "4.26898", "geospatial_lon_resolution": "0.03534", "geospatial_lon_units": "degrees_east", "geospatial_vertical_min": "0", "geospatial_vertical_max": "0.75", "geospatial_vertical_units": "m", "history": "2024-03-20T17:52:18Z data collected.2024-03-20T17:52:18Z NetCDF file created", "id": "HFR_ICATMAR_Total_2024-03-20T17:52:18Z", "institution": "Catalan Institute of Research for the Governance of the Sea", "institution_edmo_code": "5801", "L2_source_files": "RDLm_CREU_2024_03_20_1700_l2b.ruv; RDLm_AREN_2024_03_20_1700_l2b.ruv", "license": "HF radar sea surface current velocity dataset by ICATMAR is licensed under a Creative Commons Attribution 4.0 International License. You should have received a copy of the license along with this work. If not, see http://creativecommons.org/licenses/by/4.0/.", "processing_level": "3B", "publisher_name": "ICATMAR", "publisher_email": "info@icatmar.cat", "publisher_url": "https://icatmar.cat", "references": "to be defined", "source": "Surface ocean velocity field from HF-radar", "time_coverage_start": "2024-03-20T16:25:00Z", "time_coverage_end": "2024-03-20T17:40:00Z", "time_coverage_resolution": "PT1H", "title": "Near Real Time Surface Ocean Velocity", "var_names": ["u", "v", "stdu", "stdv", "gdop", "cov", "qcflag", "vart_qc", "gdop_qc", "ddns_qc", "cspd_qc"], "var_lnames": ["Surface Eastward Sea Water Velocity", "Surface Nortward Sea Water Velocity", "Standard Deviation Of Surface Eastward Sea Water Velocity", "Standard Deviation Of Surface Northward Sea Water Velocity", "Geometrical Dilution Of Precision", "Covariance Of Surface Sea Water Velocity", "Overall quality flag", "Variance threshold quality flag", "GDOP threshold quality flag", "Data density threshold quality flag", "Velocity threshold quality flag"], "var_units": ["m s-1", "m s-1", "m s-1", "m s-1", "1", "m2 s-2", "1", "1", "1", "1", "1"], "var_time": "2024-03-20T17:00:00Z"}}